Classfile /Users/houruhou/Workspace/Solarex/IDEAWorkspace/Test/out/production/Test/com/solarexsoft/test/enumtest/Main$ExceptionHandleStrategy$2.class
  Last modified Jul 2, 2018; size 938 bytes
  MD5 checksum 72c41ec7bad1139b2ef6acb36969c109
  Compiled from "Main.java"
final class com.solarexsoft.test.enumtest.Main$ExceptionHandleStrategy$2 extends com.solarexsoft.test.enumtest.Main$ExceptionHandleStrategy
  minor version: 0
  major version: 52
  flags: ACC_FINAL, ACC_SUPER, ACC_ENUM
Constant pool:
   #1 = Methodref          #6.#23         // com/solarexsoft/test/enumtest/Main$ExceptionHandleStrategy."<init>":(Ljava/lang/String;ILcom/solarexsoft/test/enumtest/Main$1;)V
   #2 = Class              #24            // java/lang/RuntimeException
   #3 = Methodref          #25.#26        // java/lang/Exception.getMessage:()Ljava/lang/String;
   #4 = Methodref          #2.#27         // java/lang/RuntimeException."<init>":(Ljava/lang/String;)V
   #5 = Class              #28            // com/solarexsoft/test/enumtest/Main$ExceptionHandleStrategy$2
   #6 = Class              #30            // com/solarexsoft/test/enumtest/Main$ExceptionHandleStrategy
   #7 = Utf8               <init>
   #8 = Utf8               (Ljava/lang/String;I)V
   #9 = Utf8               Code
  #10 = Utf8               LineNumberTable
  #11 = Utf8               LocalVariableTable
  #12 = Utf8               this
  #13 = Utf8               ExceptionHandleStrategy
  #14 = Utf8               InnerClasses
  #15 = Utf8               Lcom/solarexsoft/test/enumtest/Main$ExceptionHandleStrategy$2;
  #16 = Utf8               handle
  #17 = Utf8               (Ljava/lang/Exception;)V
  #18 = Utf8               e
  #19 = Utf8               Ljava/lang/Exception;
  #20 = Utf8               SourceFile
  #21 = Utf8               Main.java
  #22 = Utf8               EnclosingMethod
  #23 = NameAndType        #7:#32         // "<init>":(Ljava/lang/String;ILcom/solarexsoft/test/enumtest/Main$1;)V
  #24 = Utf8               java/lang/RuntimeException
  #25 = Class              #33            // java/lang/Exception
  #26 = NameAndType        #34:#35        // getMessage:()Ljava/lang/String;
  #27 = NameAndType        #7:#36         // "<init>":(Ljava/lang/String;)V
  #28 = Utf8               com/solarexsoft/test/enumtest/Main$ExceptionHandleStrategy$2
  #29 = Class              #37            // com/solarexsoft/test/enumtest/Main
  #30 = Utf8               com/solarexsoft/test/enumtest/Main$ExceptionHandleStrategy
  #31 = Class              #38            // com/solarexsoft/test/enumtest/Main$1
  #32 = Utf8               (Ljava/lang/String;ILcom/solarexsoft/test/enumtest/Main$1;)V
  #33 = Utf8               java/lang/Exception
  #34 = Utf8               getMessage
  #35 = Utf8               ()Ljava/lang/String;
  #36 = Utf8               (Ljava/lang/String;)V
  #37 = Utf8               com/solarexsoft/test/enumtest/Main
  #38 = Utf8               com/solarexsoft/test/enumtest/Main$1
{
  com.solarexsoft.test.enumtest.Main$ExceptionHandleStrategy$2(java.lang.String, int);
    descriptor: (Ljava/lang/String;I)V
    flags:
    Code:
      stack=4, locals=3, args_size=3
         0: aload_0
         1: aload_1
         2: iload_2
         3: aconst_null
         4: invokespecial #1                  // Method com/solarexsoft/test/enumtest/Main$ExceptionHandleStrategy."<init>":(Ljava/lang/String;ILcom/solarexsoft/test/enumtest/Main$1;)V
         7: return
      LineNumberTable:
        line 15: 0
      LocalVariableTable:
        Start  Length  Slot  Name   Signature
            0       8     0  this   Lcom/solarexsoft/test/enumtest/Main$ExceptionHandleStrategy$2;

  public void handle(java.lang.Exception);
    descriptor: (Ljava/lang/Exception;)V
    flags: ACC_PUBLIC
    Code:
      stack=3, locals=2, args_size=2
         0: new           #2                  // class java/lang/RuntimeException
         3: dup
         4: aload_1
         5: invokevirtual #3                  // Method java/lang/Exception.getMessage:()Ljava/lang/String;
         8: invokespecial #4                  // Method java/lang/RuntimeException."<init>":(Ljava/lang/String;)V
        11: athrow
      LineNumberTable:
        line 18: 0
      LocalVariableTable:
        Start  Length  Slot  Name   Signature
            0      12     0  this   Lcom/solarexsoft/test/enumtest/Main$ExceptionHandleStrategy$2;
            0      12     1     e   Ljava/lang/Exception;
}
SourceFile: "Main.java"
EnclosingMethod: #6.#0                  // com.solarexsoft.test.enumtest.Main$ExceptionHandleStrategy
InnerClasses:
     static #13= #6 of #29; //ExceptionHandleStrategy=class com/solarexsoft/test/enumtest/Main$ExceptionHandleStrategy of class com/solarexsoft/test/enumtest/Main
     static #5; //class com/solarexsoft/test/enumtest/Main$ExceptionHandleStrategy$2
     static #31; //class com/solarexsoft/test/enumtest/Main$1
