Classfile /Users/houruhou/Workspace/Solarex/IDEAWorkspace/Test/out/production/Test/com/solarexsoft/test/enumtest/Main$ExceptionHandleStrategy.class
  Last modified Jul 2, 2018; size 1863 bytes
  MD5 checksum 74110e6e24c135529ff942f4fc116889
  Compiled from "Main.java"
class com.solarexsoft.test.enumtest.Main$ExceptionHandleStrategy extends java.lang.Enum<com.solarexsoft.test.enumtest.Main$ExceptionHandleStrategy>
  minor version: 0
  major version: 52
  flags: ACC_SUPER, ACC_ENUM
Constant pool:
   #1 = Methodref          #5.#56         // com/solarexsoft/test/enumtest/Main$ExceptionHandleStrategy."<init>":(Ljava/lang/String;I)V
   #2 = Fieldref           #5.#57         // com/solarexsoft/test/enumtest/Main$ExceptionHandleStrategy.$VALUES:[Lcom/solarexsoft/test/enumtest/Main$ExceptionHandleStrategy;
   #3 = Methodref          #58.#59        // "[Lcom/solarexsoft/test/enumtest/Main$ExceptionHandleStrategy;".clone:()Ljava/lang/Object;
   #4 = Class              #26            // "[Lcom/solarexsoft/test/enumtest/Main$ExceptionHandleStrategy;"
   #5 = Class              #61            // com/solarexsoft/test/enumtest/Main$ExceptionHandleStrategy
   #6 = Methodref          #18.#62        // java/lang/Enum.valueOf:(Ljava/lang/Class;Ljava/lang/String;)Ljava/lang/Enum;
   #7 = Methodref          #18.#56        // java/lang/Enum."<init>":(Ljava/lang/String;I)V
   #8 = String             #21            // IGNORE
   #9 = Fieldref           #5.#63         // com/solarexsoft/test/enumtest/Main$ExceptionHandleStrategy.IGNORE:Lcom/solarexsoft/test/enumtest/Main$ExceptionHandleStrategy;
  #10 = Class              #64            // com/solarexsoft/test/enumtest/Main$ExceptionHandleStrategy$1
  #11 = String             #23            // LOG
  #12 = Methodref          #10.#56        // com/solarexsoft/test/enumtest/Main$ExceptionHandleStrategy$1."<init>":(Ljava/lang/String;I)V
  #13 = Fieldref           #5.#65         // com/solarexsoft/test/enumtest/Main$ExceptionHandleStrategy.LOG:Lcom/solarexsoft/test/enumtest/Main$ExceptionHandleStrategy;
  #14 = Class              #66            // com/solarexsoft/test/enumtest/Main$ExceptionHandleStrategy$2
  #15 = String             #24            // THROW
  #16 = Methodref          #14.#56        // com/solarexsoft/test/enumtest/Main$ExceptionHandleStrategy$2."<init>":(Ljava/lang/String;I)V
  #17 = Fieldref           #5.#67         // com/solarexsoft/test/enumtest/Main$ExceptionHandleStrategy.THROW:Lcom/solarexsoft/test/enumtest/Main$ExceptionHandleStrategy;
  #18 = Class              #68            // java/lang/Enum
  #19 = Utf8               ExceptionHandleStrategy
  #20 = Utf8               InnerClasses
  #21 = Utf8               IGNORE
  #22 = Utf8               Lcom/solarexsoft/test/enumtest/Main$ExceptionHandleStrategy;
  #23 = Utf8               LOG
  #24 = Utf8               THROW
  #25 = Utf8               $VALUES
  #26 = Utf8               [Lcom/solarexsoft/test/enumtest/Main$ExceptionHandleStrategy;
  #27 = Utf8               values
  #28 = Utf8               ()[Lcom/solarexsoft/test/enumtest/Main$ExceptionHandleStrategy;
  #29 = Utf8               Code
  #30 = Utf8               LineNumberTable
  #31 = Utf8               valueOf
  #32 = Utf8               (Ljava/lang/String;)Lcom/solarexsoft/test/enumtest/Main$ExceptionHandleStrategy;
  #33 = Utf8               LocalVariableTable
  #34 = Utf8               name
  #35 = Utf8               Ljava/lang/String;
  #36 = Utf8               <init>
  #37 = Utf8               (Ljava/lang/String;I)V
  #38 = Utf8               this
  #39 = Utf8               Signature
  #40 = Utf8               ()V
  #41 = Utf8               handle
  #42 = Utf8               (Ljava/lang/Exception;)V
  #43 = Utf8               e
  #44 = Utf8               Ljava/lang/Exception;
  #45 = Class              #69            // com/solarexsoft/test/enumtest/Main$1
  #46 = Utf8               (Ljava/lang/String;ILcom/solarexsoft/test/enumtest/Main$1;)V
  #47 = Utf8               x0
  #48 = Utf8               x1
  #49 = Utf8               I
  #50 = Utf8               x2
  #51 = Utf8               Lcom/solarexsoft/test/enumtest/Main$1;
  #52 = Utf8               <clinit>
  #53 = Utf8               Ljava/lang/Enum<Lcom/solarexsoft/test/enumtest/Main$ExceptionHandleStrategy;>;
  #54 = Utf8               SourceFile
  #55 = Utf8               Main.java
  #56 = NameAndType        #36:#37        // "<init>":(Ljava/lang/String;I)V
  #57 = NameAndType        #25:#26        // $VALUES:[Lcom/solarexsoft/test/enumtest/Main$ExceptionHandleStrategy;
  #58 = Class              #26            // "[Lcom/solarexsoft/test/enumtest/Main$ExceptionHandleStrategy;"
  #59 = NameAndType        #70:#71        // clone:()Ljava/lang/Object;
  #60 = Class              #72            // com/solarexsoft/test/enumtest/Main
  #61 = Utf8               com/solarexsoft/test/enumtest/Main$ExceptionHandleStrategy
  #62 = NameAndType        #31:#73        // valueOf:(Ljava/lang/Class;Ljava/lang/String;)Ljava/lang/Enum;
  #63 = NameAndType        #21:#22        // IGNORE:Lcom/solarexsoft/test/enumtest/Main$ExceptionHandleStrategy;
  #64 = Utf8               com/solarexsoft/test/enumtest/Main$ExceptionHandleStrategy$1
  #65 = NameAndType        #23:#22        // LOG:Lcom/solarexsoft/test/enumtest/Main$ExceptionHandleStrategy;
  #66 = Utf8               com/solarexsoft/test/enumtest/Main$ExceptionHandleStrategy$2
  #67 = NameAndType        #24:#22        // THROW:Lcom/solarexsoft/test/enumtest/Main$ExceptionHandleStrategy;
  #68 = Utf8               java/lang/Enum
  #69 = Utf8               com/solarexsoft/test/enumtest/Main$1
  #70 = Utf8               clone
  #71 = Utf8               ()Ljava/lang/Object;
  #72 = Utf8               com/solarexsoft/test/enumtest/Main
  #73 = Utf8               (Ljava/lang/Class;Ljava/lang/String;)Ljava/lang/Enum;
{
  public static final com.solarexsoft.test.enumtest.Main$ExceptionHandleStrategy IGNORE;
    descriptor: Lcom/solarexsoft/test/enumtest/Main$ExceptionHandleStrategy;
    flags: ACC_PUBLIC, ACC_STATIC, ACC_FINAL, ACC_ENUM

  public static final com.solarexsoft.test.enumtest.Main$ExceptionHandleStrategy LOG;
    descriptor: Lcom/solarexsoft/test/enumtest/Main$ExceptionHandleStrategy;
    flags: ACC_PUBLIC, ACC_STATIC, ACC_FINAL, ACC_ENUM

  public static final com.solarexsoft.test.enumtest.Main$ExceptionHandleStrategy THROW;
    descriptor: Lcom/solarexsoft/test/enumtest/Main$ExceptionHandleStrategy;
    flags: ACC_PUBLIC, ACC_STATIC, ACC_FINAL, ACC_ENUM

  public static com.solarexsoft.test.enumtest.Main$ExceptionHandleStrategy[] values();
    descriptor: ()[Lcom/solarexsoft/test/enumtest/Main$ExceptionHandleStrategy;
    flags: ACC_PUBLIC, ACC_STATIC
    Code:
      stack=1, locals=0, args_size=0
         0: getstatic     #2                  // Field $VALUES:[Lcom/solarexsoft/test/enumtest/Main$ExceptionHandleStrategy;
         3: invokevirtual #3                  // Method "[Lcom/solarexsoft/test/enumtest/Main$ExceptionHandleStrategy;".clone:()Ljava/lang/Object;
         6: checkcast     #4                  // class "[Lcom/solarexsoft/test/enumtest/Main$ExceptionHandleStrategy;"
         9: areturn
      LineNumberTable:
        line 7: 0

  public static com.solarexsoft.test.enumtest.Main$ExceptionHandleStrategy valueOf(java.lang.String);
    descriptor: (Ljava/lang/String;)Lcom/solarexsoft/test/enumtest/Main$ExceptionHandleStrategy;
    flags: ACC_PUBLIC, ACC_STATIC
    Code:
      stack=2, locals=1, args_size=1
         0: ldc           #5                  // class com/solarexsoft/test/enumtest/Main$ExceptionHandleStrategy
         2: aload_0
         3: invokestatic  #6                  // Method java/lang/Enum.valueOf:(Ljava/lang/Class;Ljava/lang/String;)Ljava/lang/Enum;
         6: checkcast     #5                  // class com/solarexsoft/test/enumtest/Main$ExceptionHandleStrategy
         9: areturn
      LineNumberTable:
        line 7: 0
      LocalVariableTable:
        Start  Length  Slot  Name   Signature
            0      10     0  name   Ljava/lang/String;

  public void handle(java.lang.Exception);
    descriptor: (Ljava/lang/Exception;)V
    flags: ACC_PUBLIC
    Code:
      stack=0, locals=2, args_size=2
         0: return
      LineNumberTable:
        line 23: 0
      LocalVariableTable:
        Start  Length  Slot  Name   Signature
            0       1     0  this   Lcom/solarexsoft/test/enumtest/Main$ExceptionHandleStrategy;
            0       1     1     e   Ljava/lang/Exception;

  com.solarexsoft.test.enumtest.Main$ExceptionHandleStrategy(java.lang.String, int, com.solarexsoft.test.enumtest.Main$1);
    descriptor: (Ljava/lang/String;ILcom/solarexsoft/test/enumtest/Main$1;)V
    flags: ACC_SYNTHETIC
    Code:
      stack=3, locals=4, args_size=4
         0: aload_0
         1: aload_1
         2: iload_2
         3: invokespecial #1                  // Method "<init>":(Ljava/lang/String;I)V
         6: return
      LineNumberTable:
        line 7: 0
      LocalVariableTable:
        Start  Length  Slot  Name   Signature
            0       7     0  this   Lcom/solarexsoft/test/enumtest/Main$ExceptionHandleStrategy;
            0       7     1    x0   Ljava/lang/String;
            0       7     2    x1   I
            0       7     3    x2   Lcom/solarexsoft/test/enumtest/Main$1;

  static {};
    descriptor: ()V
    flags: ACC_STATIC
    Code:
      stack=4, locals=0, args_size=0
         0: new           #5                  // class com/solarexsoft/test/enumtest/Main$ExceptionHandleStrategy
         3: dup
         4: ldc           #8                  // String IGNORE
         6: iconst_0
         7: invokespecial #1                  // Method "<init>":(Ljava/lang/String;I)V
        10: putstatic     #9                  // Field IGNORE:Lcom/solarexsoft/test/enumtest/Main$ExceptionHandleStrategy;
        13: new           #10                 // class com/solarexsoft/test/enumtest/Main$ExceptionHandleStrategy$1
        16: dup
        17: ldc           #11                 // String LOG
        19: iconst_1
        20: invokespecial #12                 // Method com/solarexsoft/test/enumtest/Main$ExceptionHandleStrategy$1."<init>":(Ljava/lang/String;I)V
        23: putstatic     #13                 // Field LOG:Lcom/solarexsoft/test/enumtest/Main$ExceptionHandleStrategy;
        26: new           #14                 // class com/solarexsoft/test/enumtest/Main$ExceptionHandleStrategy$2
        29: dup
        30: ldc           #15                 // String THROW
        32: iconst_2
        33: invokespecial #16                 // Method com/solarexsoft/test/enumtest/Main$ExceptionHandleStrategy$2."<init>":(Ljava/lang/String;I)V
        36: putstatic     #17                 // Field THROW:Lcom/solarexsoft/test/enumtest/Main$ExceptionHandleStrategy;
        39: iconst_3
        40: anewarray     #5                  // class com/solarexsoft/test/enumtest/Main$ExceptionHandleStrategy
        43: dup
        44: iconst_0
        45: getstatic     #9                  // Field IGNORE:Lcom/solarexsoft/test/enumtest/Main$ExceptionHandleStrategy;
        48: aastore
        49: dup
        50: iconst_1
        51: getstatic     #13                 // Field LOG:Lcom/solarexsoft/test/enumtest/Main$ExceptionHandleStrategy;
        54: aastore
        55: dup
        56: iconst_2
        57: getstatic     #17                 // Field THROW:Lcom/solarexsoft/test/enumtest/Main$ExceptionHandleStrategy;
        60: aastore
        61: putstatic     #2                  // Field $VALUES:[Lcom/solarexsoft/test/enumtest/Main$ExceptionHandleStrategy;
        64: return
      LineNumberTable:
        line 8: 0
        line 9: 13
        line 15: 26
        line 7: 39
}
Signature: #53                          // Ljava/lang/Enum<Lcom/solarexsoft/test/enumtest/Main$ExceptionHandleStrategy;>;
SourceFile: "Main.java"
InnerClasses:
     static #19= #5 of #60; //ExceptionHandleStrategy=class com/solarexsoft/test/enumtest/Main$ExceptionHandleStrategy of class com/solarexsoft/test/enumtest/Main
     static #14; //class com/solarexsoft/test/enumtest/Main$ExceptionHandleStrategy$2
     static #10; //class com/solarexsoft/test/enumtest/Main$ExceptionHandleStrategy$1
     static #45; //class com/solarexsoft/test/enumtest/Main$1
